odoo/addons/report_pdf_form/README.rst
odoo/addons/report_pdf_form/__init__.py
odoo/addons/report_pdf_form/__manifest__.py
odoo/addons/report_pdf_form/i18n/it.po
odoo/addons/report_pdf_form/i18n/nl.po
odoo/addons/report_pdf_form/i18n/report_pdf_form.pot
odoo/addons/report_pdf_form/models/__init__.py
odoo/addons/report_pdf_form/models/ir_actions_report.py
odoo/addons/report_pdf_form/models/report_pdf_form.py
odoo/addons/report_pdf_form/models/report_pdf_form_field.py
odoo/addons/report_pdf_form/models/report_pdf_form_variable.py
odoo/addons/report_pdf_form/readme/CONFIGURATION.md
odoo/addons/report_pdf_form/readme/CONTRIBUTORS.md
odoo/addons/report_pdf_form/readme/DESCRIPTION.md
odoo/addons/report_pdf_form/readme/ROADMAP.md
odoo/addons/report_pdf_form/security/ir.model.access.csv
odoo/addons/report_pdf_form/static/description/icon.png
odoo/addons/report_pdf_form/static/description/index.html
odoo/addons/report_pdf_form/tests/__init__.py
odoo/addons/report_pdf_form/tests/test_report_pdf_form.py
odoo/addons/report_pdf_form/tests/data/form_example.pdf
odoo/addons/report_pdf_form/tests/data/form_example.sla
odoo/addons/report_pdf_form/views/report_pdf_form.xml
odoo_addon_report_pdf_form-18.0.1.0.0.6.dist-info/METADATA
odoo_addon_report_pdf_form-18.0.1.0.0.6.dist-info/WHEEL
odoo_addon_report_pdf_form-18.0.1.0.0.6.dist-info/top_level.txt
odoo_addon_report_pdf_form-18.0.1.0.0.6.dist-info/RECORD
